ladder/__init__.py
ladder/__meta__.py
ladder/_compat.py
ladder/ladder.py
ladder/ospath.py
ladder/delimitedpath.py
ladder/api.py
ladder/utils.py
ladder/urlpath.py
ladder-0.4.1.dist-info/top_level.txt
ladder-0.4.1.dist-info/METADATA
ladder-0.4.1.dist-info/DESCRIPTION.rst
ladder-0.4.1.dist-info/metadata.json
ladder-0.4.1.dist-info/WHEEL
ladder-0.4.1.dist-info/RECORD
