Metadata-Version: 2.0
Name: ladder
Version: 0.4.1
Summary: General purpose path generation library with support for URLs, OS paths, delimited paths, and RESTful HTTP client integration.
Home-page: https://github.com/dgilland/ladder
Author: Derrick Gilland
Author-email: dgilland@gmail.com
License: MIT License
Platform: UNKNOWN
Classifier: Development Status :: 4 - Beta
Classifier: Intended Audience :: Developers
Classifier: Operating System :: OS Independent
Classifier: License :: OSI Approved :: MIT License
Classifier: Topic :: Software Development :: Libraries :: Python Modules
Classifier: Programming Language :: Python
Classifier: Programming Language :: Python :: 2.6
Classifier: Programming Language :: Python :: 2.7
Classifier: Programming Language :: Python :: 3.2
Classifier: Programming Language :: Python :: 3.3
